jupyter_mcp/__init__.py
jupyter_mcp/__main__.py
jupyter_mcp/__version__.py
jupyter_mcp/application.py
jupyter_mcp/serverapplication.py
jupyter_mcp/handlers/__init__.py
jupyter_mcp/handlers/base.py
jupyter_mcp/handlers/config/__init__.py
jupyter_mcp/handlers/config/handler.py
jupyter_mcp/handlers/index/__init__.py
jupyter_mcp/handlers/index/handler.py
jupyter_mcp/handlers/oauth/__init__.py
jupyter_mcp/handlers/oauth/handler.py
jupyter_mcp/static/README.md
jupyter_mcp/templates/index.html
jupyter_mcp/tests/__init__.py
jupyter_mcp/tests/test_handlers.py
jupyter_mcp-0.0.1.data/data/etc/jupyter/jupyter_notebook_config.d/jupyter_iam.json
jupyter_mcp-0.0.1.data/data/etc/jupyter/jupyter_server_config.d/jupyter_iam.json
jupyter_mcp-0.0.1.dist-info/METADATA
jupyter_mcp-0.0.1.dist-info/WHEEL
jupyter_mcp-0.0.1.dist-info/entry_points.txt
jupyter_mcp-0.0.1.dist-info/licenses/LICENSE
jupyter_mcp-0.0.1.dist-info/RECORD
